[
  {
    "Event": "CHALLENGE",
    "Points": 3500,
    "TeamID": "101"
  },
  {
    "Event": "CHALLENGE",
    "Points": 3500,
    "TeamID": "106"
  },
  {
    "Event": "CHALLENGE",
    "Points": 3000,
    "TeamID": "112"
  },
  {
    "Event": "CHALLENGE",
    "Points": 2775,
    "TeamID": "115"
  },
  {
    "Event": "CHALLENGE",
    "Points": 2550,
    "TeamID": "110"
  },
  {
    "Event": "CHALLENGE",
    "Points": 2425,
    "TeamID": "117"
  },
  {
    "Event": "CHALLENGE",
    "Points": 2175,
    "TeamID": "102"
  },
  {
    "Event": "CHALLENGE",
    "Points": 2175,
    "TeamID": "124"
  },
  {
    "Event": "CHALLENGE",
    "Points": 2125,
    "TeamID": "104"
  },
  {
    "Event": "CHALLENGE",
    "Points": 1975,
    "TeamID": "114"
  },
  {
    "Event": "CHALLENGE",
    "Points": 1875,
    "TeamID": "120"
  },
  {
    "Event": "CHALLENGE",
    "Points": 1825,
    "TeamID": "116"
  },
  {
    "Event": "CHALLENGE",
    "Points": 1750,
    "TeamID": "123"
  },
  {
    "Event": "CHALLENGE",
    "Points": 1650,
    "TeamID": "125"
  },
  {
    "Event": "CHALLENGE",
    "Points": 1625,
    "TeamID": "105"
  },
  {
    "Event": "CHALLENGE",
    "Points": 1550,
    "TeamID": "109"
  },
  {
    "Event": "CHALLENGE",
    "Points": 1450,
    "TeamID": "108"
  },
  {
    "Event": "CHALLENGE",
    "Points": 1350,
    "TeamID": "122"
  },
  {
    "Event": "CHALLENGE",
    "Points": 1100,
    "TeamID": "121"
  },
  {
    "Event": "CHALLENGE",
    "Points": 0,
    "TeamID": "100"
  },
  {
    "Event": "CHALLENGE",
    "Points": 0,
    "TeamID": "103"
  },
  {
    "Event": "CHALLENGE",
    "Points": 0,
    "TeamID": "107"
  },
  {
    "Event": "CHALLENGE",
    "Points": 0,
    "TeamID": "111"
  },
  {
    "Event": "CHALLENGE",
    "Points": 0,
    "TeamID": "113"
  },
  {
    "Event": "CHALLENGE",
    "Points": 0,
    "TeamID": "118"
  },
  {
    "Event": "CHALLENGE",
    "Points": 0,
    "TeamID": "119"
  }
]